{
  "id": "plan_1765101633725",
  "title": "Test",
  "description": "Test",
  "status": "active",
  "createdAt": "2025-12-07T10:00:33.725Z",
  "updatedAt": "2025-12-07T10:00:33.726Z",
  "steps": [
    {
      "id": 0,
      "action": "A",
      "status": "completed",
      "tools": [],
      "validation": "",
      "critical": false,
      "dependencies": [],
      "result": null,
      "startedAt": null,
      "completedAt": "2025-12-07T10:00:33.726Z"
    },
    {
      "id": 1,
      "action": "B",
      "status": "completed",
      "tools": [],
      "validation": "",
      "critical": false,
      "dependencies": [],
      "result": null,
      "startedAt": null,
      "completedAt": "2025-12-07T10:00:33.726Z"
    },
    {
      "id": 2,
      "action": "C",
      "status": "completed",
      "tools": [],
      "validation": "",
      "critical": false,
      "dependencies": [],
      "result": null,
      "startedAt": null,
      "completedAt": "2025-12-07T10:00:33.726Z"
    },
    {
      "id": 3,
      "action": "D",
      "status": "completed",
      "tools": [],
      "validation": "",
      "critical": false,
      "dependencies": [],
      "result": null,
      "startedAt": null,
      "completedAt": "2025-12-07T10:00:33.726Z"
    }
  ],
  "risks": [],
  "dependencies": [],
  "estimatedDuration": null,
  "actualDuration": null,
  "metadata": {}
}